{
  "id": "347116",
  "actors": "",
  "airs_dayofweek": "",
  "airs_time": "",
  "contentrating": "",
  "firstaired": "2015-08-27",
  "genre": "|Horror|Suspense|Thriller|",
  "imdb_id": "tt4993722",
  "language": "hu",
  "network": "",
  "networkid": "",
  "overview": "Fueled by nostalgia, this anthology of short horror films tells original tales of terror set during the Halloween season.",
  "rating": "0",
  "ratingcount": "0",
  "runtime": "15",
  "seriesid": "",
  "status": "Ended",
  "added": "2018-05-02 08:49:32",
  "addedby": "",
  "banner": "series/347116/banners/5e961985b8a7c.jpg",
  "fanart": "fanart/original/5c7d75bd021d1.jpg",
  "lastupdated": "1586895239",
  "poster": "posters/5b9cdcf4e22e9.jpg",
  "zap2it_id": "",
  "name": "The Witching Season",
  "episodes": [
    {
      "id": "6677574",
      "dvd_chapter": "0",
      "dvd_discid": "",
      "dvd_episodenumber": "0",
      "dvd_season": "0",
      "director": "|Michael Ballif|",
      "epimgflag": "",
      "episodenumber": "1",
      "firstaired": "2015-08-27",
      "gueststars": "|Autumn Russell|Hailey Nebeker|James Morris|",
      "imdb_id": "",
      "language": "hu",
      "overview": "",
      "productioncode": "",
      "rating": "0",
      "ratingcount": "0",
      "seasonnumber": "1",
      "writer": "|Michael Ballif|",
      "absolute_number": "0",
      "airsafter_season": "0",
      "airsbefore_episode": "0",
      "airsbefore_season": "0",
      "filename": "episodes/347116/6677574.jpg",
      "lastupdated": "1551726370",
      "seasonid": "763536",
      "seriesid": "347116",
      "thumb_added": "2019-11-13 11:38:56",
      "thumb_height": "360",
      "thumb_width": "640",
      "name": "Killer on the Loose",
      "number": 1,
      "season": 1
    },
    {
      "id": "6677575",
      "dvd_chapter": "0",
      "dvd_discid": "",
      "dvd_episodenumber": "0",
      "dvd_season": "0",
      "director": "|James Morris|",
      "epimgflag": "",
      "episodenumber": "2",
      "firstaired": "2015-10-30",
      "gueststars": "|Anita Rosenbaum|Emily Broschinsky|James Morris|Jordan Swenson|",
      "imdb_id": "",
      "language": "hu",
      "overview": "",
      "productioncode": "",
      "rating": "0",
      "ratingcount": "0",
      "seasonnumber": "1",
      "writer": "|James Morris|",
      "absolute_number": "0",
      "airsafter_season": "0",
      "airsbefore_episode": "0",
      "airsbefore_season": "0",
      "filename": "episodes/347116/6677575.jpg",
      "lastupdated": "1551726441",
      "seasonid": "763536",
      "seriesid": "347116",
      "thumb_added": "2019-11-13 11:38:56",
      "thumb_height": "360",
      "thumb_width": "640",
      "name": "Princess",
      "number": 2,
      "season": 1
    },
    {
      "id": "6677576",
      "dvd_chapter": "0",
      "dvd_discid": "",
      "dvd_episodenumber": "0",
      "dvd_season": "0",
      "director": "|James Morris|",
      "epimgflag": "",
      "episodenumber": "3",
      "firstaired": "2016-04-25",
      "gueststars": "|Samuel Morris|Sean Hunter|",
      "imdb_id": "",
      "language": "hu",
      "overview": "",
      "productioncode": "",
      "rating": "0",
      "ratingcount": "0",
      "seasonnumber": "1",
      "writer": "|James Morris|Michael Ballif|",
      "absolute_number": "0",
      "airsafter_season": "0",
      "airsbefore_episode": "0",
      "airsbefore_season": "0",
      "filename": "episodes/347116/6677576.jpg",
      "lastupdated": "1551726498",
      "seasonid": "763536",
      "seriesid": "347116",
      "thumb_added": "2019-11-13 11:38:56",
      "thumb_height": "360",
      "thumb_width": "640",
      "name": "Not Alone",
      "number": 3,
      "season": 1
    },
    {
      "id": "6677577",
      "dvd_chapter": "0",
      "dvd_discid": "",
      "dvd_episodenumber": "0",
      "dvd_season": "0",
      "director": "|Michael Ballif|",
      "epimgflag": "",
      "episodenumber": "4",
      "firstaired": "2016-11-19",
      "gueststars": "|James Morris|Stevie Dutson|",
      "imdb_id": "",
      "language": "hu",
      "overview": "",
      "productioncode": "",
      "rating": "0",
      "ratingcount": "0",
      "seasonnumber": "1",
      "writer": "|Caroman Turner|David Harris|Michael Ballif|",
      "absolute_number": "0",
      "airsafter_season": "0",
      "airsbefore_episode": "0",
      "airsbefore_season": "0",
      "filename": "episodes/347116/6677577.jpg",
      "lastupdated": "1551726556",
      "seasonid": "763536",
      "seriesid": "347116",
      "thumb_added": "2019-11-13 11:38:56",
      "thumb_height": "360",
      "thumb_width": "640",
      "name": "The Live Inside Us",
      "number": 4,
      "season": 1
    },
    {
      "id": "6677583",
      "dvd_chapter": "0",
      "dvd_discid": "",
      "dvd_episodenumber": "0",
      "dvd_season": "0",
      "director": "|James Morris|",
      "epimgflag": "",
      "episodenumber": "5",
      "firstaired": "2017-05-13",
      "gueststars": "|Charla Cochran Bocchicchio|James Morris|Karlee Broschinsky|Samuel Morris|",
      "imdb_id": "",
      "language": "hu",
      "overview": "",
      "productioncode": "",
      "rating": "0",
      "ratingcount": "0",
      "seasonnumber": "1",
      "writer": "|James Morris|Michael Ballif|",
      "absolute_number": "0",
      "airsafter_season": "0",
      "airsbefore_episode": "0",
      "airsbefore_season": "0",
      "filename": "episodes/347116/6677583.jpg",
      "lastupdated": "1551726623",
      "seasonid": "763536",
      "seriesid": "347116",
      "thumb_added": "2019-11-13 11:38:56",
      "thumb_height": "360",
      "thumb_width": "640",
      "name": "Is That You?",
      "number": 5,
      "season": 1
    }
  ]
}